Workbook

Sheet Payroll 
A4: Sum of TOTAL | B4: Payroll
A5: Location | B5: Agro | C5: Aroor | D5: Breads | E5: Green | F5: Hosur | G5: Kalamassery | H5: Mumbai | I5: YRFM | J5: Grand Total
A6: Agro | B6: 452982.71 | F6: 36808.631 | I6: 80949.322 | J6: 570740.66
A7: Ahmedabad | E7: 266366.68 | J7: 266366.68
A8: Aroor | C8: 687464.74 | G8: 13121.73 | I8: 25691.5 | J8: 726277.97
A9: Breads | B9: 56268.999 | C9: 46571.5 | D9: 539270.31 | F9: 147792.32 | I9: 85646.648 | J9: 875549.78
A10: Corporate | B10: 705912.15 | C10: 497953.5 | D10: 612679.67 | F10: 713622.04 | G10: 1850154.5 | H10: 86872.668 | I10: 1697414.8 | J10: 6164609.3
A11: Gardenia | B11: 17758.765 | G11: 33571.5 | J11: 51330.265
A12: Hosur | B12: 9128.16 | D12: 46831.5 | F12: 1225839.8 | G12: 61886.8 | I12: 50709.97 | J12: 1394396.3
A13: Indore | E13: 195907.85 | I13: 72643 | J13: 268550.85
A14: Kalamassery | B14: 19070.989 | G14: 807463.99 | I14: 57593 | J14: 884127.98
A15: Mumbai | G15: 123585.35 | H15: 559053.49 | I15: 21603.2 | J15: 704242.04
A16: Organic | B16: 13811.793 | E16: 665947.74 | I16: 71852.703 | J16: 751612.24
A17: Outsourcing | B17: 9128.16 | D17: 10269.18 | F17: 184271.45 | I17: 15403.77 | J17: 219072.56
A18: YRFM | B18: 81102.823 | D18: 91290.921 | I18: 1520051.8 | J18: 1692445.5
A19: Grand Total | B19: 1365164.5 | C19: 1231989.7 | D19: 1300341.6 | E19: 1128222.3 | F19: 2308334.3 | G19: 2889783.9 | H19: 645926.16 | I19: 3699559.6 | J19: 14569322
A22: Sum of TOTAL | B22: Payroll
A23: Division | B23: AGRO | C23: AROOR | D23: Bread | E23: Hosur | F23: KALAMASSERY | G23: Mumbai | H23: YRFM | I23: Grand Total
A24: Agro Sales | B24: 149144.44 | H24: 16843.65 | I24: 165988.09
A25: Andhrapradesh | E25: 218450.4 | I25: 218450.4
A26: Bulk | H26: 274865.48 | I26: 274865.48
A27: Cake Plus | B27: 25546.202 | C27: 74158.548 | D27: 17930.656 | F27: 66322.492 | I27: 183957.9
A28: CPS 1 | B28: 18222.299 | H28: 323229.19 | I28: 341451.49
A29: CPS Star | B29: 502692.72 | C29: 49687.69 | D29: 17703.822 | F29: 14036.375 | H29: 535759.33 | I29: 1119879.9
A30: Delhi | G30: 24303.6 | I30: 24303.6
A31: Gujarat | G31: 90249.604 | I31: 90249.604
A32: Karnataka | E32: 307015.16 | H32: 303148.35 | I32: 610163.51
A33: Mumbai | B33: 18416.728 | G33: 345407.15 | I33: 363823.88
A34: North Kerala - Breads | B34: 16418.432 | D34: 117178.4 | H34: 15799.344 | I34: 149396.17
A35: North Kerala - Cakes | B35: 14676.434 | D35: 16990.917 | F35: 48347.501 | H35: 39261.5 | I35: 119276.35
A36: Premix | B36: 60041.5 | I36: 60041.5
A37: South Kerala - Breads | C37: 87757.718 | F37: 45681.5 | H37: 47341.886 | I37: 180781.1
A38: South Kerala - Cakes | C38: 37891.5 | F38: 140102.78 | I38: 177994.28
A39: Tamil Nadu | D39: 127241.5 | E39: 48660.6 | H39: 697728.4 | I39: 873630.5
A40: Grand Total | B40: 805158.76 | C40: 249495.46 | D40: 297045.29 | E40: 574126.15 | F40: 314490.65 | G40: 459960.36 | H40: 2253977.1 | I40: 4954253.8
A44: Sum of TOTAL | B44: Payroll
A45: Division | B45: Agro | E45: Hosur | G45: Mumbai | H45: YRFM | I45: Grand Total
A46: Agro Sales | B46: 30131.9 | I46: 30131.9
A47: Bulk | B47: 26242.407 | H47: 192984.28 | I47: 219226.68
A48: CPS 1 | B48: 13048.214 | I48: 13048.214
A49: CPS Star | B49: 550938.01 | H49: 118326.02 | I49: 669264.03
A50: Karnataka | E50: 30678.876 | I50: 30678.876
A51: Mumbai | G51: 28841.5 | I51: 28841.5
A52: Tamilnadu | E52: 50071.654 | H52: 19982.96 | I52: 70054.614
A53: Grand Total | B53: 620360.53 | E53: 80750.53 | G53: 28841.5 | H53: 331293.26 | I53: 1061245.8

Sheet Sheet1
A1: Sl.No. | B1: SAP NO | C1: Name | D1: Designation | E1: DOJ | F1: Band | G1: Gross Salary | H1: Salary | I1: New Division | J1: Department | K1: Payroll | L1: ESI | M1: PF | N1: Total
A2: 1 | B2: 9 | C2: A Shalu | D2: =VLOOKUP(B2,[2]sales!$B$2:$D$183,3,0) -> Territory Sales Manager | E2: 01.01.1993 | F2: P3 | G2: =VLOOKUP(B2,[9]Staff!B$7:H$245,7,0) -> 45090 | H2: =VLOOKUP(B2,[9]Staff!B$7:P$245,15,0) -> 45090 | I2: =VLOOKUP(B2,[2]sales!$B$2:$G$183,6,0) -> Bulk | J2: Bulk | K2: YRFM | L2: =IF(H2>23335,0,(H2*90%*4.75%)) -> 0 | M2: =IF(H2*60%*12%>1800,1974,(H2*60%*13.16%)) -> 1974 | N2: =H2+L2+M2 -> 47064
A3: 2 | B3: 27 | C3: M R Rajesh Kumar | D3: =VLOOKUP(B3,[2]sales!$B$2:$D$183,3,0) -> Sales Manager | E3: 01.11.1997 | F3: M2 | G3: =VLOOKUP(B3,[9]Staff!B$7:H$245,7,0) -> 66250 | H3: =VLOOKUP(B3,[9]Staff!B$7:P$245,15,0) -> 66250 | I3: =VLOOKUP(B3,[2]sales!$B$2:$G$183,6,0) -> Bulk | J3: Bulk | K3: YRFM | L3: =IF(H3>23335,0,(H3*90%*4.75%)) -> 0 | M3: =IF(H3*60%*12%>1800,1974,(H3*60%*13.16%)) -> 1974 | N3: =H3+L3+M3 -> 68224
A4: 3 | B4: 1667 | C4: Biby Boban | D4: =VLOOKUP(B4,[2]sales!$B$2:$D$183,3,0) -> Territory Sales Manager | E4: 01.10.2010 | F4: M1 | G4: =VLOOKUP(B4,[9]Staff!B$7:H$245,7,0) -> 42090 | H4: =VLOOKUP(B4,[9]Staff!B$7:P$245,15,0) -> 42090 | I4: =VLOOKUP(B4,[2]sales!$B$2:$G$183,6,0) -> Bulk | J4: Bulk | K4: YRFM | L4: =IF(H4>23335,0,(H4*90%*4.75%)) -> 0 | M4: =IF(H4*60%*12%>1800,1974,(H4*60%*13.16%)) -> 1974 | N4: =H4+L4+M4 -> 44064
A5: 4 | B5: 4553 | C5: Baburajan Parakkal | D5: =VLOOKUP(B5,[2]sales!$B$2:$D$183,3,0) -> Territory Sales Executive | E5: 22.12.2017 | F5: S1 | G5: =VLOOKUP(B5,[9]Staff!B$7:H$245,7,0) -> 17000 | H5: =VLOOKUP(B5,[9]Staff!B$7:P$245,15,0) -> 17000 | I5: =VLOOKUP(B5,[2]sales!$B$2:$G$183,6,0) -> Bulk | J5: Bulk | K5: YRFM | L5: =IF(H5>23335,0,(H5*90%*4.75%)) -> 726.75 | M5: =IF(H5*60%*12%>1800,1974,(H5*60%*13.16%)) -> 1342.32 | N5: =H5+L5+M5 -> 19069.07
A6: 5 | B6: 31 | C6: K Jayakumar | D6: =VLOOKUP(B6,[2]sales!$B$2:$D$183,3,0) -> Area Sales Manager | E6: 02.06.2000 | F6: M1 | G6: =VLOOKUP(B6,[9]Staff!B$7:H$245,7,0) -> 44490 | H6: =VLOOKUP(B6,[9]Staff!B$7:P$245,15,0) -> 44490 | I6: =VLOOKUP(B6,[2]sales!$B$2:$G$183,6,0) -> Tamilnadu | J6: Tamil Nadu | K6: YRFM | L6: =IF(H6>23335,0,(H6*90%*4.75%)) -> 0 | M6: =IF(H6*60%*12%>1800,1974,(H6*60%*13.16%)) -> 1974 | N6: =H6+L6+M6 -> 46464
A7: 6 | B7: 4528 | C7: P.Balamurugan | D7: =VLOOKUP(B7,[2]sales!$B$2:$D$183,3,0) -> Territory Sales Executive | E7: 06.12.2017 | F7: S1 | G7: =VLOOKUP(B7,'[5]Hosur-Apr''18'!B$5:H$127,7,0) -> 16000 | H7: =VLOOKUP(B7,'[5]Hosur-Apr''18'!B$5:M$127,12,0) -> 16000 | I7: =VLOOKUP(B7,[2]sales!$B$2:$G$183,6,0) -> Tamilnadu | J7: Tamil Nadu | K7: Hosur | L7: =IF(H7>21000,0,(H7*4.75%)) -> 760 | M7: =IF(H7*70%*12%>1800,1974,(H7*70%*12%)) -> 1344 | N7: =H7+L7+M7 -> 18104
A8: 7 | B8: 4580 | C8: Karthikeyan.M | D8: =VLOOKUP(B8,[2]sales!$B$2:$D$183,3,0) -> Territory Sales Executive | E8: 01.02.2018 | F8: S1 | G8: =VLOOKUP(B8,'[5]Hosur-Apr''18'!B$5:H$127,7,0) -> 21100 | H8: =VLOOKUP(B8,'[5]Hosur-Apr''18'!B$5:M$127,12,0) -> 21100 | I8: =VLOOKUP(B8,[2]sales!$B$2:$G$183,6,0) -> Tamilnadu | J8: Tamil Nadu | K8: Hosur | L8: =IF(H8>21000,0,(H8*4.75%)) -> 0 | M8: =IF(H8*70%*12%>1800,1974,(H8*70%*12%)) -> 1772.4 | N8: =H8+L8+M8 -> 22872.4
A9: 8 | B9: 36 | C9: Sunil A V | D9: =VLOOKUP(B9,[2]sales!$B$2:$D$183,3,0) -> Territory Sales Executive | E9: 06.07.2004 | F9: S1 | G9: =VLOOKUP(B9,[9]Staff!B$7:H$245,7,0) -> 28690 | H9: =VLOOKUP(B9,[9]Staff!B$7:P$245,15,0) -> 28690 | I9: =VLOOKUP(B9,[2]sales!$B$2:$G$183,6,0) -> CPD North | J9: CPD | K9: YRFM | L9: =IF(H9>23335,0,(H9*90%*4.75%)) -> 0 | M9: =IF(H9*60%*12%>1800,1974,(H9*60%*13.16%)) -> 1974 | N9: =H9+L9+M9 -> 30664
A10: 9 | B10: 4583 | C10: Sujith.M | D10: =VLOOKUP(B10,[2]sales!$B$2:$D$183,3,0) -> Sr. Territory Sales Executive | E10: 05.02.18 | F10: S2 | G10: =VLOOKUP(B10,'[6]staff klmsy (2)'!$B$7:I$84,8,0) -> 25500 | H10: =VLOOKUP(B10,'[6]staff klmsy (2)'!B$7:R$84,17,0) -> 25500 | I10: =VLOOKUP(B10,[2]sales!$B$2:$G$183,6,0) -> CPD North | J10: CPD | K10: Kalamassery | L10: =IF(H10>23335,0,(H10*90%*4.75%)) -> 0 | M10: =IF(H10*60%*12%>1800,1974,(H10*60%*13.16%)) -> 1974 | N10: =H10+L10+M10 -> 27474
A11: 10 | B11: 259 | C11: Thomas Abraham | D11: =VLOOKUP(B11,[2]sales!$B$2:$D$183,3,0) -> Area Sales Manager | E11: 01.12.2004 | F11: M2 | G11: =VLOOKUP(B11,'[4]salary aroor'!B$7:H$52,7,0) -> 44400 | H11: =VLOOKUP(B11,'[4]salary aroor'!B$7:L$52,11,0) -> 44400 | I11: =VLOOKUP(B11,[2]sales!$B$2:$G$183,6,0) -> CPD South | J11: CPD | K11: Aroor | L11: =IF(H11>23335,0,(H11*90%*4.75%)) -> 0 | M11: =IF(H11*60%*12%>1800,1974,(H11*60%*13.16%)) -> 1974 | N11: =H11+L11+M11 -> 46374
A12: 11 | B12: 285 | C12: Santhosh Kumar | D12: =VLOOKUP(B12,[2]sales!$B$2:$D$183,3,0) -> Sr. Territory Sales Executive | E12: 01.04.2006 | F12: S2 | G12: =VLOOKUP(B12,'[4]salary aroor'!B$7:H$52,7,0) -> 29310 | H12: =VLOOKUP(B12,'[4]salary aroor'!B$7:L$52,11,0) -> 29310 | I12: =VLOOKUP(B12,[2]sales!$B$2:$G$183,6,0) -> Bakery South | J12: Bakery-South | K12: Aroor | L12: =IF(H12>23335,0,(H12*90%*4.75%)) -> 0 | M12: =IF(H12*60%*12%>1800,1974,(H12*60%*13.16%)) -> 1974 | N12: =H12+L12+M12 -> 31284
A13: 12 | B13: 555 | C13: Rajeev K L | D13: =VLOOKUP(B13,[2]sales!$B$2:$D$183,3,0) -> Sr. Territory Sales Executive | E13: 01.03.2001 | F13: P2 | G13: =VLOOKUP(B13,'[3]april (2)'!B$8:H$132,7,0) -> 29910 | H13: =VLOOKUP(B13,'[3]april (2)'!B$8:N$132,13,0) -> 29910 | I13: =VLOOKUP(B13,[2]sales!$B$2:$G$183,6,0) -> Institution Sales | J13: Agro Sales | K13: Agro | L13: =IF(H13>23335,0,(H13*90%*4.75%)) -> 0 | M13: =IF(H13*60%*12%>1800,1974,(H13*60%*13.16%)) -> 1974 | N13: =H13+L13+M13 -> 31884
A14: 13 | B14: 567 | C14: Manikandan T | D14: =VLOOKUP(B14,[2]sales!$B$2:$D$183,3,0) -> Area Sales Manager | E14: 14.03.2005 | F14: M1 | G14: =VLOOKUP(B14,'[3]april (2)'!B$8:H$132,7,0) -> 41300 | H14: =VLOOKUP(B14,'[3]april (2)'!B$8:N$132,13,0) -> 41300 | I14: =VLOOKUP(B14,[2]sales!$B$2:$G$183,6,0) -> Institution Sales | J14: Agro Sales | K14: Agro | L14: =IF(H14>23335,0,(H14*90%*4.75%)) -> 0 | M14: =IF(H14*60%*12%>1800,1974,(H14*60%*13.16%)) -> 1974 | N14: =H14+L14+M14 -> 43274
A15: 14 | B15: 731 | C15: K C Reghunath | D15: =VLOOKUP(B15,[2]sales!$B$2:$D$183,3,0) -> Sr. Territory Sales Executive | E15: 01.05.2008 | F15: S2 | G15: =VLOOKUP(B15,[9]Staff!B$7:H$245,7,0) -> 19780 | H15: =VLOOKUP(B15,[9]Staff!B$7:P$245,15,0) -> 19780 | I15: =VLOOKUP(B15,[2]sales!$B$2:$G$183,6,0) -> Bulk | J15: Bulk | K15: YRFM | L15: =IF(H15>23335,0,(H15*90%*4.75%)) -> 845.595 | M15: =IF(H15*60%*12%>1800,1974,(H15*60%*13.16%)) -> 1561.8288 | N15: =H15+L15+M15 -> 22187.424
A16: 15 | B16: 808 | C16: Sujesh K T | D16: =VLOOKUP(B16,[2]sales!$B$2:$D$183,3,0) -> Territory Sales Executive | E16: 01.10.2008 | F16: S1 | G16: =VLOOKUP(B16,[9]Staff!B$7:H$245,7,0) -> 19140 | H16: =VLOOKUP(B16,[9]Staff!B$7:P$245,15,0) -> 19140 | I16: =VLOOKUP(B16,[2]sales!$B$2:$G$183,6,0) -> Institution Sales | J16: Agro Sales | K16: YRFM | L16: =IF(H16>23335,0,(H16*90%*4.75%)) -> 818.235 | M16: =IF(H16*60%*12%>1800,1974,(H16*60%*13.16%)) -> 1511.2944 | N16: =H16+L16+M16 -> 21469.529
A17: 16 | B17: 904 | C17: Sunil Kumar K | D17: =VLOOKUP(B17,[2]sales!$B$2:$D$183,3,0) -> Territory Sales Manager | E17: 01.04.2008 | F17: P3 | G17: =VLOOKUP(B17,'[8]Tasty Toast-Apr''18'!B$5:H$61,7,0) -> 26990 | H17: =VLOOKUP(B17,'[8]Tasty Toast-Apr''18'!B$5:N$61,13,0) -> 26990 | I17: =VLOOKUP(B17,[2]sales!$B$2:$G$183,6,0) -> Bakery South | J17: Bakery-South | K17: Breads | L17: =IF(H17>21000,0,(H17*4.75%)) -> 0 | M17: =IF(H17*70%*12%>1800,1974,(H17*70%*12%)) -> 1974 | N17: =H17+L17+M17 -> 28964
A18: 17 | B18: 1056 | C18: K M Girish Kumar | D18: =VLOOKUP(B18,[2]sales!$B$2:$D$183,3,0) -> Sr. Territory Sales Executive | E18: 22.12.2008 | F18: S2 | G18: =VLOOKUP(B18,[9]Staff!B$7:H$245,7,0) -> 19020 | H18: =VLOOKUP(B18,[9]Staff!B$7:P$245,15,0) -> 19020 | I18: =VLOOKUP(B18,[2]sales!$B$2:$G$183,6,0) -> Bulk | J18: Bulk | K18: YRFM | L18: =IF(H18>23335,0,(H18*90%*4.75%)) -> 813.105 | M18: =IF(H18*60%*12%>1800,1974,(H18*60%*13.16%)) -> 1501.8192 | N18: =H18+L18+M18 -> 21334.924
A19: 18 | B19: 1210 | C19: Govind S Menon | D19: Sales Coordinator | E19: 25.06.2008 | F19: M1 | G19: =VLOOKUP(B19,'[6]staff klmsy (2)'!$B$7:I$84,8,0) -> 38120 | H19: =VLOOKUP(B19,'[6]staff klmsy (2)'!B$7:R$84,17,0) -> 38120 | I19: Bulk | J19: Bulk | K19: Kalamassery | L19: =IF(H19>23335,0,(H19*90%*4.75%)) -> 0 | M19: =IF(H19*60%*12%>1800,1974,(H19*60%*13.16%)) -> 1974 | N19: =H19+L19+M19 -> 40094
A20: 19 | B20: 1213 | C20: Rajeesh .P | D20: =VLOOKUP(B20,[2]sales!$B$2:$D$183,3,0) -> Territory Sales Executive | E20: 01.11.2008 | F20: S2 | G20: =VLOOKUP(B20,'[6]staff klmsy (2)'!$B$7:I$84,8,0) -> 17450 | H20: =VLOOKUP(B20,'[6]staff klmsy (2)'!B$7:R$84,17,0) -> 17450 | I20: =VLOOKUP(B20,[2]sales!$B$2:$G$183,6,0) -> Bakery North | J20: Bakery-North | K20: Kalamassery | L20: =IF(H20>23335,0,(H20*90%*4.75%)) -> 745.9875 | M20: =IF(H20*60%*12%>1800,1974,(H20*60%*13.16%)) -> 1377.852 | N20: =H20+L20+M20 -> 19573.839
A21: 20 | B21: 1221 | C21: Abbas.B | D21: =VLOOKUP(B21,[2]sales!$B$2:$D$183,3,0) -> Territory Sales Executive | E21: 12.06.2009 | F21: S2 | G21: =VLOOKUP(B21,'[6]staff klmsy (2)'!$B$7:I$84,8,0) -> 25030 | H21: =VLOOKUP(B21,'[6]staff klmsy (2)'!B$7:R$84,17,0) -> 25030 | I21: =VLOOKUP(B21,[2]sales!$B$2:$G$183,6,0) -> Bakery South | J21: Bakery-South | K21: Kalamassery | L21: =IF(H21>23335,0,(H21*90%*4.75%)) -> 0 | M21: =IF(H21*60%*12%>1800,1974,(H21*60%*13.16%)) -> 1974 | N21: =H21+L21+M21 -> 27004
A22: 21 | B22: 1256 | C22: Unnikrishnan M | D22: Mechandiser | E22: 28.09.2009 | F22: F2 | G22: =VLOOKUP(B22,[9]Staff!B$7:H$245,7,0) -> 14840 | H22: =VLOOKUP(B22,[9]Staff!B$7:P$245,15,0) -> 14840 | I22: Institutional Sales | J22: Institutional Sales | K22: YRFM | L22: =IF(H22>23335,0,(H22*90%*4.75%)) -> 634.41 | M22: =IF(H22*60%*12%>1800,1974,(H22*60%*13.16%)) -> 1171.7664 | N22: =H22+L22+M22 -> 16646.176
A23: 22 | B23: 1276 | C23: Gopinathan K | D23: =VLOOKUP(B23,[2]sales!$B$2:$D$183,3,0) -> Territory Sales Executive | E23: 07.09.2009 | F23: S2 | G23: =VLOOKUP(B23,'[8]Tasty Toast-Apr''18'!B$5:H$61,7,0) -> 20650 | H23: =VLOOKUP(B23,'[8]Tasty Toast-Apr''18'!B$5:N$61,13,0) -> 20650 | I23: =VLOOKUP(B23,[2]sales!$B$2:$G$183,6,0) -> Bakery North | J23: CPD | K23: Breads | L23: =IF(H23>21000,0,(H23*4.75%)) -> 980.875 | M23: =IF(H23*70%*12%>1800,1974,(H23*70%*12%)) -> 1734.6 | N23: =H23+L23+M23 -> 23365.475
A24: 23 | B24: 4554 | C24: R.Suriyan | D24: =VLOOKUP(B24,[2]sales!$B$2:$D$183,3,0) -> Territory Sales Executive | E24: 06.01.2018 | F24: S1 | G24: =VLOOKUP(B24,'[5]Hosur-Apr''18'!B$5:H$127,7,0) -> 12500 | H24: =VLOOKUP(B24,'[5]Hosur-Apr''18'!B$5:M$127,12,0) -> 12500 | I24: =VLOOKUP(B24,[2]sales!$B$2:$G$183,6,0) -> Tamilnadu | K24: Hosur | L24: =IF(H24>21000,0,(H24*4.75%)) -> 593.75 | M24: =IF(H24*70%*12%>1800,1974,(H24*70%*12%)) -> 1050 | N24: =H24+L24+M24 -> 14143.75
A25: 24 | B25: 1397 | C25: Jayakumar K P | D25: =VLOOKUP(B25,[2]sales!$B$2:$D$183,3,0) -> Territory Sales Executive | E25: 01.09.2010 | F25: S1 | G25: =VLOOKUP(B25,[9]Staff!B$7:H$245,7,0) -> 15070 | H25: =VLOOKUP(B25,[9]Staff!B$7:P$245,15,0) -> 15070 | I25: =VLOOKUP(B25,[2]sales!$B$2:$G$183,6,0) -> Bulk | J25: Bulk | K25: YRFM | L25: =IF(H25>23335,0,(H25*90%*4.75%)) -> 644.2425 | M25: =IF(H25*60%*12%>1800,1974,(H25*60%*13.16%)) -> 1189.9272 | N25: =H25+L25+M25 -> 16904.17
A26: 25 | B26: 1420 | C26: Prasanth V B | D26: =VLOOKUP(B26,[2]sales!$B$2:$D$183,3,0) -> Sr. Territory Sales Executive | E26: 10.03.2010 | F26: S2 | G26: =VLOOKUP(B26,[9]Staff!B$7:H$245,7,0) -> 22090 | H26: =VLOOKUP(B26,[9]Staff!B$7:P$245,15,0) -> 22090 | I26: =VLOOKUP(B26,[2]sales!$B$2:$G$183,6,0) -> CPD North | J26: CPD | K26: YRFM | L26: =IF(H26>23335,0,(H26*90%*4.75%)) -> 944.3475 | M26: =IF(H26*60%*12%>1800,1974,(H26*60%*13.16%)) -> 1744.2264 | N26: =H26+L26+M26 -> 24778.574
A27: 26 | B27: 1423 | C27: Kalesh Kumar | D27: =VLOOKUP(B27,[2]sales!$B$2:$D$183,3,0) -> Territory Sales Executive | E27: 20.11.2009 | F27: S2 | G27: =VLOOKUP(B27,'[6]staff klmsy (2)'!$B$7:I$84,8,0) -> 21190 | H27: =VLOOKUP(B27,'[6]staff klmsy (2)'!B$7:R$84,17,0) -> 9888.67 | I27: =VLOOKUP(B27,[2]sales!$B$2:$G$183,6,0) -> Bakery South | J27: Bakery-South | K27: Kalamassery | L27: =IF(H27>23335,0,(H27*90%*4.75%)) -> 422.74064 | M27: =IF(H27*60%*12%>1800,1974,(H27*60%*13.16%)) -> 780.80938 | N27: =H27+L27+M27 -> 11092.22
A28: 27 | B28: 1450 | C28: S Mohan Kumar | D28: =VLOOKUP(B28,[2]sales!$B$2:$D$183,3,0) -> Territory Sales Executive | E28: 01.04.2010 | F28: S1 | G28: =VLOOKUP(B28,[9]Staff!B$7:H$245,7,0) -> 17720 | H28: =VLOOKUP(B28,[9]Staff!B$7:P$245,15,0) -> 17720 | I28: =VLOOKUP(B28,[2]sales!$B$2:$G$183,6,0) -> CPD South | J28: CPD | K28: YRFM | L28: =IF(H28>23335,0,(H28*90%*4.75%)) -> 757.53 | M28: =IF(H28*60%*12%>1800,1974,(H28*60%*13.16%)) -> 1399.1712 | N28: =H28+L28+M28 -> 19876.701
A29: 28 | B29: 1467 | C29: Selvan R | D29: =VLOOKUP(B29,[2]sales!$B$2:$D$183,3,0) -> Territory Sales Manager | E29: 12.04.2010 | F29: P3 | G29: =VLOOKUP(B29,'[4]salary aroor'!B$7:H$52,7,0) -> 29100 | H29: =VLOOKUP(B29,'[4]salary aroor'!B$7:L$52,11,0) -> 29100 | I29: Snacks | J29: Bread & Cakes | K29: Aroor | L29: =IF(H29>23335,0,(H29*90%*4.75%)) -> 0 | M29: =IF(H29*60%*12%>1800,1974,(H29*60%*13.16%)) -> 1974 | N29: =H29+L29+M29 -> 31074
A30: 29 | B30: 4960 | C30: Anu.E.J | D30: Sales Representative | E30: 10.04.2018 | F30: F2 | G30: =VLOOKUP(B30,'[4]salary aroor'!B$7:H$52,7,0) -> 12500 | H30: =VLOOKUP(B30,'[4]salary aroor'!B$7:L$52,11,0) -> 9875 | I30: Snacks | K30: Aroor | L30: =IF(H30>23335,0,(H30*90%*4.75%)) -> 422.15625 | M30: =IF(H30*60%*12%>1800,1974,(H30*60%*13.16%)) -> 779.73 | N30: =H30+L30+M30 -> 11076.886
A31: 30 | B31: 4961 | C31: Vipin Kumar.V | D31: Sales Representative | E31: 10.04.2018 | F31: F2 | G31: =VLOOKUP(B31,'[4]salary aroor'!B$7:H$52,7,0) -> 13000 | H31: =VLOOKUP(B31,'[4]salary aroor'!B$7:L$52,11,0) -> 10270 | I31: Snacks | K31: Aroor | L31: =IF(H31>23335,0,(H31*90%*4.75%)) -> 439.0425 | M31: =IF(H31*60%*12%>1800,1974,(H31*60%*13.16%)) -> 810.9192 | N31: =H31+L31+M31 -> 11519.962
A32: 31 | B32: 1525 | C32: Navaneeth Krishnan | D32: =VLOOKUP(B32,[2]sales!$B$2:$D$183,3,0) -> Sr. Territory Sales Executive | E32: 16.06.2010 | F32: S2 | G32: =VLOOKUP(B32,[9]Staff!B$7:H$245,7,0) -> 21630 | H32: =VLOOKUP(B32,[9]Staff!B$7:P$245,15,0) -> 21630 | I32: =VLOOKUP(B32,[2]sales!$B$2:$G$183,6,0) -> Modern Trade | J32: Modern Trade | K32: YRFM | L32: =IF(H32>23335,0,(H32*90%*4.75%)) -> 924.6825 | M32: =IF(H32*60%*12%>1800,1974,(H32*60%*13.16%)) -> 1707.9048 | N32: =H32+L32+M32 -> 24262.587
A33: 32 | B33: 1526 | C33: Sunil Kumar N.P. | D33: Merchandiser | E33: 14.06.2010 | F33: F2 | G33: =VLOOKUP(B33,'[8]Tasty Toast-Apr''18'!B$5:H$61,7,0) -> 21830 | H33: =VLOOKUP(B33,'[8]Tasty Toast-Apr''18'!B$5:N$61,13,0) -> 21830 | I33: North Kerala Bakery | J33: Bread & Cakes | K33: Breads | L33: =IF(H33>21000,0,(H33*4.75%)) -> 0 | M33: =IF(H33*70%*12%>1800,1974,(H33*70%*12%)) -> 1974 | N33: =H33+L33+M33 -> 23804
A34: 33 | B34: 1546 | C34: Sudheer Babu P. | D34: =VLOOKUP(B34,[2]sales!$B$2:$D$183,3,0) -> Territory Sales Executive | E34: 28.06.2010 | F34: S1 | G34: =VLOOKUP(B34,'[8]Tasty Toast-Apr''18'!B$5:H$61,7,0) -> 21180 | H34: =VLOOKUP(B34,'[8]Tasty Toast-Apr''18'!B$5:N$61,13,0) -> 21180 | I34: =VLOOKUP(B34,[2]sales!$B$2:$G$183,6,0) -> Modern Trade | J34: Modern Trade | K34: Breads | L34: =IF(H34>21000,0,(H34*4.75%)) -> 0 | M34: =IF(H34*70%*12%>1800,1974,(H34*70%*12%)) -> 1779.12 | N34: =H34+L34+M34 -> 22959.12
A35: 34 | B35: 1617 | C35: Sreelal R | D35: =VLOOKUP(B35,[2]sales!$B$2:$D$183,3,0) -> Sr. Territory Sales Executive | E35: 01.02.2011 | F35: S2 | G35: =VLOOKUP(B35,[9]Staff!B$7:H$245,7,0) -> 23440 | H35: =VLOOKUP(B35,[9]Staff!B$7:P$245,15,0) -> 23440 | I35: =VLOOKUP(B35,[2]sales!$B$2:$G$183,6,0) -> Modern Trade | J35: Modern Trade | K35: YRFM | L35: =IF(H35>23335,0,(H35*90%*4.75%)) -> 0 | M35: =IF(H35*60%*12%>1800,1974,(H35*60%*13.16%)) -> 1850.8224 | N35: =H35+L35+M35 -> 25290.822
A36: 35 | B36: 1676 | C36: Suresh Kumar | D36: =VLOOKUP(B36,[2]sales!$B$2:$D$183,3,0) -> Territory Sales Manager | E36: 06.10.2010 | F36: P3 | G36: =VLOOKUP(B36,'[6]staff klmsy (2)'!$B$7:I$84,8,0) -> 32800 | H36: =VLOOKUP(B36,'[6]staff klmsy (2)'!B$7:R$84,17,0) -> 32800 | I36: =VLOOKUP(B36,[2]sales!$B$2:$G$183,6,0) -> Bakery South | J36: Bread & Cakes | K36: Kalamassery | L36: =IF(H36>23335,0,(H36*90%*4.75%)) -> 0 | M36: =IF(H36*60%*12%>1800,1974,(H36*60%*13.16%)) -> 1974 | N36: =H36+L36+M36 -> 34774
A37: 36 | B37: 1682 | C37: Dinesh K G | D37: =VLOOKUP(B37,[2]sales!$B$2:$D$183,3,0) -> Regional Sales Manager | E37: 25.10.2010 | F37: SM1 | G37: =VLOOKUP(B37,[9]Staff!B$7:H$245,7,0) -> 131880 | H37: =VLOOKUP(B37,[9]Staff!B$7:P$245,15,0) -> 131880 | I37: =VLOOKUP(B37,[2]sales!$B$2:$G$183,6,0) -> Karnataka | J37: Karnataka | K37: YRFM | L37: =IF(H37>23335,0,(H37*90%*4.75%)) -> 0 | M37: =IF(H37*60%*12%>1800,1974,(H37*60%*13.16%)) -> 1974 | N37: =H37+L37+M37 -> 133854
A38: 37 | B38: 1747 | C38: Riyas S | D38: =VLOOKUP(B38,[2]sales!$B$2:$D$183,3,0) -> Territory Sales Executive | E38: 06.12.2010 | F38: S1 | G38: =VLOOKUP(B38,[9]Staff!B$7:H$245,7,0) -> 21680 | H38: =VLOOKUP(B38,[9]Staff!B$7:P$245,15,0) -> 21680 | I38: =VLOOKUP(B38,[2]sales!$B$2:$G$183,6,0) -> Bulk | J38: CPD | K38: YRFM | L38: =IF(H38>23335,0,(H38*90%*4.75%)) -> 926.82 | M38: =IF(H38*60%*12%>1800,1974,(H38*60%*13.16%)) -> 1711.8528 | N38: =H38+L38+M38 -> 24318.673
A39: 38 | B39: 4575 | C39: P.Naresh | D39: =VLOOKUP(B39,[2]sales!$B$2:$D$183,3,0) -> Sr. Territory Sales Executive | E39: 29.01.2018 | F39: S2 | G39: =VLOOKUP(B39,'[5]Hosur-Apr''18'!B$5:H$127,7,0) -> 30000 | H39: =VLOOKUP(B39,'[5]Hosur-Apr''18'!B$5:M$127,12,0) -> 30000 | I39: =VLOOKUP(B39,[2]sales!$B$2:$G$183,6,0) -> AP | J39: Karnataka | K39: Hosur | L39: =IF(H39>21000,0,(H39*4.75%)) -> 0 | M39: =IF(H39*70%*12%>1800,1974,(H39*70%*12%)) -> 1974 | N39: =H39+L39+M39 -> 31974
A40: 39 | B40: 4576 | C40: T.Amit Singh | D40: =VLOOKUP(B40,[2]sales!$B$2:$D$183,3,0) -> Territory Sales Executive | E40: 24.01.2018 | F40: S1 | G40: =VLOOKUP(B40,'[5]Hosur-Apr''18'!B$5:H$127,7,0) -> 21001 | H40: =VLOOKUP(B40,'[5]Hosur-Apr''18'!B$5:M$127,12,0) -> 21001 | I40: =VLOOKUP(B40,[2]sales!$B$2:$G$183,6,0) -> AP | J40: Karnataka | K40: Hosur | L40: =IF(H40>21000,0,(H40*4.75%)) -> 0 | M40: =IF(H40*70%*12%>1800,1974,(H40*70%*12%)) -> 1764.084 | N40: =H40+L40+M40 -> 22765.084
A41: 40 | B41: 4883 | C41: M.Prasanna Kumar | D41: =VLOOKUP(B41,[2]sales!$B$2:$D$183,3,0) -> Territory Sales Executive | E41: 19.02.2018 | F41: S1 | G41: =VLOOKUP(B41,'[5]Hosur-Apr''18'!B$5:H$127,7,0) -> 26500 | H41: =VLOOKUP(B41,'[5]Hosur-Apr''18'!B$5:M$127,12,0) -> 26500 | I41: =VLOOKUP(B41,[2]sales!$B$2:$G$183,6,0) -> AP | J41: Andhrapradesh | K41: Hosur | L41: =IF(H41>21000,0,(H41*4.75%)) -> 0 | M41: =IF(H41*70%*12%>1800,1974,(H41*70%*12%)) -> 1974 | N41: =H41+L41+M41 -> 28474
A42: 41 | B42: 4958 | C42: J.Mithun | D42: Area Sales Manager | E42: 05.04.2018 | F42: M2 | G42: =VLOOKUP(B42,'[5]Hosur-Apr''18'!B$5:H$127,7,0) -> 62500 | H42: =VLOOKUP(B42,'[5]Hosur-Apr''18'!B$5:M$127,12,0) -> 54250 | I42: AP | K42: Hosur | L42: =IF(H42>21000,0,(H42*4.75%)) -> 0 | M42: =IF(H42*70%*12%>1800,1974,(H42*70%*12%)) -> 1974 | N42: =H42+L42+M42 -> 56224
A43: 42 | B43: 1850 | C43: Pandirajan | D43: =VLOOKUP(B43,[2]sales!$B$2:$D$183,3,0) -> Sr.Area Sales Manager | E43: 31.03.2011 | F43: M2 | G43: =VLOOKUP(B43,[9]Staff!B$7:H$245,7,0) -> 81480 | H43: =VLOOKUP(B43,[9]Staff!B$7:P$245,15,0) -> 81480 | I43: =VLOOKUP(B43,[2]sales!$B$2:$G$183,6,0) -> Tamilnadu | J43: Tamil Nadu | K43: YRFM | L43: =IF(H43>23335,0,(H43*90%*4.75%)) -> 0 | M43: =IF(H43*60%*12%>1800,1974,(H43*60%*13.16%)) -> 1974 | N43: =H43+L43+M43 -> 83454
A44: 43 | B44: 2043 | C44: Nasim Abdul Karim A M | D44: =VLOOKUP(B44,[2]sales!$B$2:$D$183,3,0) -> Sr. Territory Sales Executive | E44: 05.05.2011 | F44: S2 | G44: =VLOOKUP(B44,[9]Staff!B$7:H$245,7,0) -> 21810 | H44: =VLOOKUP(B44,[9]Staff!B$7:P$245,15,0) -> 21810 | I44: =VLOOKUP(B44,[2]sales!$B$2:$G$183,6,0) -> Bulk | J44: Bulk | K44: YRFM | L44: =IF(H44>23335,0,(H44*90%*4.75%)) -> 932.3775 | M44: =IF(H44*60%*12%>1800,1974,(H44*60%*13.16%)) -> 1722.1176 | N44: =H44+L44+M44 -> 24464.495
A45: 44 | B45: 2118 | C45: Harikumar S | D45: Van Sales Representative | E45: 27.06.2011 | F45: S1 | G45: =VLOOKUP(B45,[9]Staff!B$7:H$245,7,0) -> 16310 | H45: =VLOOKUP(B45,[9]Staff!B$7:P$245,15,0) -> 16310 | I45: CPD | J45: CPD | K45: YRFM | L45: =IF(H45>23335,0,(H45*90%*4.75%)) -> 697.2525 | M45: =IF(H45*60%*12%>1800,1974,(H45*60%*13.16%)) -> 1287.8376 | N45: =H45+L45+M45 -> 18295.09
A46: 45 | B46: 2204 | C46: Sasidharan K.M | D46: =VLOOKUP(B46,[2]sales!$B$2:$D$183,3,0) -> Territory Sales Executive | E46: 07.07.2011 | F46: S1 | G46: =VLOOKUP(B46,'[8]Tasty Toast-Apr''18'!B$5:H$61,7,0) -> 14500 | H46: =VLOOKUP(B46,'[8]Tasty Toast-Apr''18'!B$5:N$61,13,0) -> 14500 | I46: =VLOOKUP(B46,[2]sales!$B$2:$G$183,6,0) -> Bakery North | J46: Bread & Cakes | K46: Breads | L46: =IF(H46>21000,0,(H46*4.75%)) -> 688.75 | M46: =IF(H46*70%*12%>1800,1974,(H46*70%*12%)) -> 1218 | N46: =H46+L46+M46 -> 16406.75
A47: 46 | B47: 2205 | C47: Balachander N | D47: =VLOOKUP(B47,[2]sales!$B$2:$D$183,3,0) -> Regional Manager | E47: 11.07.2011 | F47: SM3 | G47: 151870 | H47: 151870 | I47: =VLOOKUP(B47,[2]sales!$B$2:$G$183,6,0) -> Tamilnadu | J47: Tamil Nadu | K47: Breads | L47: =IF(H47>21000,0,(H47*4.75%)) -> 0 | M47: =IF(H47*70%*12%>1800,1974,(H47*70%*12%)) -> 1974 | N47: =H47+L47+M47 -> 153844
A48: 47 | B48: 2249 | C48: Pradeep B S | D48: Merchandiser | E48: 25.07.2011 | F48: S1 | G48: =VLOOKUP(B48,[9]Staff!B$7:H$245,7,0) -> 17710 | H48: =VLOOKUP(B48,[9]Staff!B$7:P$245,15,0) -> 1180.67 | I48: CPD | J48: CPD | K48: YRFM | L48: =IF(H48>23335,0,(H48*90%*4.75%)) -> 50.473642 | M48: =IF(H48*60%*12%>1800,1974,(H48*60%*13.16%)) -> 93.225703 | N48: =H48+L48+M48 -> 1324.3693
A49: 48 | B49: 4558 | C49: K.Paramashivan | D49: =VLOOKUP(B49,[2]sales!$B$2:$D$183,3,0) -> Territory Sales Executive | E49: 10.01.2018 | F49: S1 | G49: =VLOOKUP(B49,'[5]Hosur-Apr''18'!B$5:H$127,7,0) -> 17500 | H49: =VLOOKUP(B49,'[5]Hosur-Apr''18'!B$5:M$127,12,0) -> 17500 | I49: =VLOOKUP(B49,[2]sales!$B$2:$G$183,6,0) -> Tamilnadu | J49: Tamil Nadu | K49: Hosur | L49: =IF(H49>21000,0,(H49*4.75%)) -> 831.25 | M49: =IF(H49*70%*12%>1800,1974,(H49*70%*12%)) -> 1470 | N49: =H49+L49+M49 -> 19801.25
A50: 49 | B50: 5008 | C50: T.Mavendhan | D50: SalesTrainee | E50: 21.04.2018 | F50: S1 | G50: =VLOOKUP(B50,'[5]Hosur-Apr''18'!B$5:H$127,7,0) -> 16500 | H50: =VLOOKUP(B50,'[5]Hosur-Apr''18'!B$5:M$127,12,0) -> 5478 | I50: Tamilnadu | K50: Hosur | L50: =IF(H50>21000,0,(H50*4.75%)) -> 260.205 | M50: =IF(H50*70%*12%>1800,1974,(H50*70%*12%)) -> 460.152 | N50: =H50+L50+M50 -> 6198.357
A51: 50 | B51: 5010 | C51: V.Balaji | D51: Territory Sales Manager | E51: 23.04.2018 | F51: P3 | G51: =VLOOKUP(B51,'[5]Hosur-Apr''18'!B$5:H$127,7,0) -> 34500 | H51: =VLOOKUP(B51,'[5]Hosur-Apr''18'!B$5:M$127,12,0) -> 9246 | I51: Tamilnadu | K51: Hosur | L51: =IF(H51>21000,0,(H51*4.75%)) -> 439.185 | M51: =IF(H51*70%*12%>1800,1974,(H51*70%*12%)) -> 776.664 | N51: =H51+L51+M51 -> 10461.849
A52: 51 | B52: 2370 | C52: Sajan M. Samuel | D52: =VLOOKUP(B52,[2]sales!$B$2:$D$183,3,0) -> Regional Sales Manager | E52: 12.09.2011 | F52: SM1 | G52: =VLOOKUP(B52,[9]Staff!B$7:H$245,7,0) -> 87130 | H52: =VLOOKUP(B52,[9]Staff!B$7:P$245,15,0) -> 87130 | I52: =VLOOKUP(B52,[2]sales!$B$2:$G$183,6,0) -> CPD South | J52: CPD | K52: YRFM | L52: =IF(H52>23335,0,(H52*90%*4.75%)) -> 0 | M52: =IF(H52*60%*12%>1800,1974,(H52*60%*13.16%)) -> 1974 | N52: =H52+L52+M52 -> 89104
A53: 52 | B53: 2409 | C53: D.Kumar | D53: =VLOOKUP(B53,[2]sales!$B$2:$D$183,3,0) -> Area Sales Manager | E53: 20.09.2011 | F53: M1 | G53: =VLOOKUP(B53,[9]Staff!B$7:H$245,7,0) -> 68050 | H53: =VLOOKUP(B53,[9]Staff!B$7:P$245,15,0) -> 68050 | I53: =VLOOKUP(B53,[2]sales!$B$2:$G$183,6,0) -> Tamilnadu | J53: Tamil Nadu | K53: YRFM | L53: =IF(H53>23335,0,(H53*90%*4.75%)) -> 0 | M53: =IF(H53*60%*12%>1800,1974,(H53*60%*13.16%)) -> 1974 | N53: =H53+L53+M53 -> 70024
A54: 53 | B54: 4882 | C54: Mohan Raj.G | D54: =VLOOKUP(B54,[2]sales!$B$2:$D$183,3,0) -> Territory Sales Executive | E54: 19.02.2018 | F54: S1 | G54: =VLOOKUP(B54,'[5]Hosur-Apr''18'!B$5:H$127,7,0) -> 25000 | H54: =VLOOKUP(B54,'[5]Hosur-Apr''18'!B$5:M$127,12,0) -> 25000 | I54: =VLOOKUP(B54,[2]sales!$B$2:$G$183,6,0) -> Tamilnadu | J54: Tamil Nadu | K54: Hosur | L54: =IF(H54>21000,0,(H54*4.75%)) -> 0 | M54: =IF(H54*70%*12%>1800,1974,(H54*70%*12%)) -> 1974 | N54: =H54+L54+M54 -> 26974
A55: 54 | B55: 2410 | C55: M. Durairaj | D55: =VLOOKUP(B55,[2]sales!$B$2:$D$183,3,0) -> Sr. Territory Sales Executive | E55: 26.09.2011 | F55: S2 | G55: =VLOOKUP(B55,[9]Staff!B$7:H$245,7,0) -> 25870 | H55: =VLOOKUP(B55,[9]Staff!B$7:P$245,15,0) -> 25870 | I55: =VLOOKUP(B55,[2]sales!$B$2:$G$183,6,0) -> Tamilnadu | J55: Tamil Nadu | K55: YRFM | L55: =IF(H55>23335,0,(H55*90%*4.75%)) -> 0 | M55: =IF(H55*60%*12%>1800,1974,(H55*60%*13.16%)) -> 1974 | N55: =H55+L55+M55 -> 27844
A56: 55 | B56: 2506 | C56: T. Sudhakar | D56: =VLOOKUP(B56,[2]sales!$B$2:$D$183,3,0) -> Territory Sales Executive | E56: 09.11.2011 | F56: S1 | G56: =VLOOKUP(B56,[9]Staff!B$7:H$245,7,0) -> 23840 | H56: =VLOOKUP(B56,[9]Staff!B$7:P$245,15,0) -> 23840 | I56: =VLOOKUP(B56,[2]sales!$B$2:$G$183,6,0) -> Tamilnadu | J56: Modern Trade | K56: YRFM | L56: =IF(H56>23335,0,(H56*90%*4.75%)) -> 0 | M56: =IF(H56*60%*12%>1800,1974,(H56*60%*13.16%)) -> 1882.4064 | N56: =H56+L56+M56 -> 25722.406
A57: 56 | B57: 2568 | C57: Shaheed V.S | D57: =VLOOKUP(B57,[2]sales!$B$2:$D$183,3,0) -> Sr. Territory Sales Executive | E57: 02.12.2011 | F57: S2 | G57: =VLOOKUP(B57,'[6]staff klmsy (2)'!$B$7:I$84,8,0) -> 21450 | H57: =VLOOKUP(B57,'[6]staff klmsy (2)'!B$7:R$84,17,0) -> 21450 | I57: =VLOOKUP(B57,[2]sales!$B$2:$G$183,6,0) -> Institution Sales | J57: Institutional Sales | K57: Kalamassery | L57: =IF(H57>23335,0,(H57*90%*4.75%)) -> 916.9875 | M57: =IF(H57*60%*12%>1800,1974,(H57*60%*13.16%)) -> 1693.692 | N57: =H57+L57+M57 -> 24060.679
A58: 57 | B58: 2690 | C58: Gireesh Kumar .A | D58: Territory Sales Manager | E58: 19.03.2012 | F58: P3 | G58: =VLOOKUP(B58,'[4]salary aroor'!B$7:H$52,7,0) -> 23160 | H58: =VLOOKUP(B58,'[4]salary aroor'!B$7:L$52,11,0) -> 23160 | I58: =VLOOKUP(B58,[2]sales!$B$2:$G$183,6,0) -> Bakery South | J58: Bread &Cake | K58: Aroor | L58: =IF(H58>23335,0,(H58*90%*4.75%)) -> 990.09 | M58: =IF(H58*60%*12%>1800,1974,(H58*60%*13.16%)) -> 1828.7136 | N58: =H58+L58+M58 -> 25978.804
A59: 58 | B59: 2692 | C59: Riyasudheen B. | D59: =VLOOKUP(B59,[2]sales!$B$2:$D$183,3,0) -> Territory Sales Executive | E59: 16.04.2012 | F59: S1 | G59: =VLOOKUP(B59,[9]Staff!B$7:H$245,7,0) -> 17210 | H59: =VLOOKUP(B59,[9]Staff!B$7:P$245,15,0) -> 17210 | I59: =VLOOKUP(B59,[2]sales!$B$2:$G$183,6,0) -> CPD North | J59: CPD | K59: YRFM | L59: =IF(H59>23335,0,(H59*90%*4.75%)) -> 735.7275 | M59: =IF(H59*60%*12%>1800,1974,(H59*60%*13.16%)) -> 1358.9016 | N59: =H59+L59+M59 -> 19304.629
A60: 59 | B60: 2693 | C60: Balu V Das | D60: =VLOOKUP(B60,[2]sales!$B$2:$D$183,3,0) -> Territory Sales Executive | E60: 16.04.2012 | F60: S1 | G60: =VLOOKUP(B60,[9]Staff!B$7:H$245,7,0) -> 14560 | H60: =VLOOKUP(B60,[9]Staff!B$7:P$245,15,0) -> 14560 | I60: =VLOOKUP(B60,[2]sales!$B$2:$G$183,6,0) -> Bulk | J60: Bulk | K60: YRFM | L60: =IF(H60>23335,0,(H60*90%*4.75%)) -> 622.44 | M60: =IF(H60*60%*12%>1800,1974,(H60*60%*13.16%)) -> 1149.6576 | N60: =H60+L60+M60 -> 16332.098
A61: 60 | B61: 4503 | C61: Bashayir Ahamed.M.S | D61: =VLOOKUP(B61,[2]sales!$B$2:$D$183,3,0) -> Territory Sales Executive | E61: 24.11.2017 | F61: S1 | G61: =VLOOKUP(B61,'[5]Hosur-Apr''18'!B$5:H$127,7,0) -> 18000 | H61: =VLOOKUP(B61,'[5]Hosur-Apr''18'!B$5:M$127,12,0) -> 18000 | I61: =VLOOKUP(B61,[2]sales!$B$2:$G$183,6,0) -> Tamilnadu | J61: Tamil Nadu | K61: Hosur | L61: =IF(H61>21000,0,(H61*4.75%)) -> 855 | M61: =IF(H61*70%*12%>1800,1974,(H61*70%*12%)) -> 1512 | N61: =H61+L61+M61 -> 20367
A62: 61 | B62: 2719 | C62: Girisha R | D62: =VLOOKUP(B62,[2]sales!$B$2:$D$183,3,0) -> Area Sales Manager | E62: 23.04.2012 | F62: P3 | G62: =VLOOKUP(B62,[9]Staff!B$7:H$245,7,0) -> 65000 | H62: =VLOOKUP(B62,[9]Staff!B$7:P$245,15,0) -> 65000 | I62: =VLOOKUP(B62,[2]sales!$B$2:$G$183,6,0) -> Karnataka | J62: Karnataka | K62: YRFM | L62: =IF(H62>23335,0,(H62*90%*4.75%)) -> 0 | M62: =IF(H62*60%*12%>1800,1974,(H62*60%*13.16%)) -> 1974 | N62: =H62+L62+M62 -> 66974
A63: 62 | B63: 4881 | C63: Harish Mirajkar | D63: =VLOOKUP(B63,[2]sales!$B$2:$D$183,3,0) -> Sr. Territory Sales Executive | E63: 19.02.2018 | F63: S2 | G63: =VLOOKUP(B63,'[5]Hosur-Apr''18'!B$5:H$127,7,0) -> 37500 | H63: =VLOOKUP(B63,'[5]Hosur-Apr''18'!B$5:M$127,12,0) -> 37500 | I63: =VLOOKUP(B63,[2]sales!$B$2:$G$183,6,0) -> Karnataka | J63: Karnataka | K63: Hosur | L63: =IF(H63>21000,0,(H63*4.75%)) -> 0 | M63: =IF(H63*70%*12%>1800,1974,(H63*70%*12%)) -> 1974 | N63: =H63+L63+M63 -> 39474
A64: 63 | B64: 2791 | C64: Nobil P T | D64: =VLOOKUP(B64,[2]sales!$B$2:$D$183,3,0) -> Territory Sales Executive | E64: 18.06.2012 | F64: S1 | G64: =VLOOKUP(B64,[9]Staff!B$7:H$245,7,0) -> 17110 | H64: =VLOOKUP(B64,[9]Staff!B$7:P$245,15,0) -> 17110 | I64: =VLOOKUP(B64,[2]sales!$B$2:$G$183,6,0) -> Bulk | J64: Bulk | K64: YRFM | L64: =IF(H64>23335,0,(H64*90%*4.75%)) -> 731.4525 | M64: =IF(H64*60%*12%>1800,1974,(H64*60%*13.16%)) -> 1351.0056 | N64: =H64+L64+M64 -> 19192.458
A65: 64 | B65: 2809 | C65: Vinaya Prasad M P | D65: =VLOOKUP(B65,[2]sales!$B$2:$D$183,3,0) -> Area Sales Manager | E65: 09.07.2012 | F65: M1 | G65: =VLOOKUP(B65,[9]Staff!B$7:H$245,7,0) -> 65000 | H65: =VLOOKUP(B65,[9]Staff!B$7:P$245,15,0) -> 65000 | I65: =VLOOKUP(B65,[2]sales!$B$2:$G$183,6,0) -> Karnataka | J65: Karnataka | K65: YRFM | L65: =IF(H65>23335,0,(H65*90%*4.75%)) -> 0 | M65: =IF(H65*60%*12%>1800,1974,(H65*60%*13.16%)) -> 1974 | N65: =H65+L65+M65 -> 66974
A66: 65 | B66: 2839 | C66: Rajesh Kumar R | D66: =VLOOKUP(B66,[2]sales!$B$2:$D$183,3,0) -> Territory Sales Executive | E66: 11.07.2012 | F66: S1 | G66: =VLOOKUP(B66,[9]Staff!B$7:H$245,7,0) -> 18610 | H66: =VLOOKUP(B66,[9]Staff!B$7:P$245,15,0) -> 18610 | I66: =VLOOKUP(B66,[2]sales!$B$2:$G$183,6,0) -> CPD South | J66: CPD | K66: YRFM | L66: =IF(H66>23335,0,(H66*90%*4.75%)) -> 795.5775 | M66: =IF(H66*60%*12%>1800,1974,(H66*60%*13.16%)) -> 1469.4456 | N66: =H66+L66+M66 -> 20875.023
A67: 66 | B67: 2847 | C67: Sudheesh Kumar Mk | D67: =VLOOKUP(B67,[2]sales!$B$2:$D$183,3,0) -> Territory Sales Executive | E67: 01.08.2012 | F67: S1 | G67: =VLOOKUP(B67,[9]Staff!B$7:H$245,7,0) -> 20630 | H67: =VLOOKUP(B67,[9]Staff!B$7:P$245,15,0) -> 20630 | I67: =VLOOKUP(B67,[2]sales!$B$2:$G$183,6,0) -> CPD South | J67: CPD | K67: YRFM | L67: =IF(H67>23335,0,(H67*90%*4.75%)) -> 881.9325 | M67: =IF(H67*60%*12%>1800,1974,(H67*60%*13.16%)) -> 1628.9448 | N67: =H67+L67+M67 -> 23140.877
A68: 67 | B68: 2871 | C68: Mathews Devasia | D68: =VLOOKUP(B68,[2]sales!$B$2:$D$183,3,0) -> Territory Sales Executive | E68: 10.09.2012 | F68: S1 | G68: =VLOOKUP(B68,[9]Staff!B$7:H$245,7,0) -> 15390 | H68: =VLOOKUP(B68,[9]Staff!B$7:P$245,15,0) -> 15390 | I68: =VLOOKUP(B68,[2]sales!$B$2:$G$183,6,0) -> Bakery South | J68: Bread &Cakes | K68: YRFM | L68: =IF(H68>23335,0,(H68*90%*4.75%)) -> 657.9225 | M68: =IF(H68*60%*12%>1800,1974,(H68*60%*13.16%)) -> 1215.1944 | N68: =H68+L68+M68 -> 17263.117
A69: 68 | B69: 2925 | C69: Ajith A.G | D69: =VLOOKUP(B69,[2]sales!$B$2:$D$183,3,0) -> Territory Sales Manager | E69: 01.10.2012 | F69: P3 | G69: =VLOOKUP(B69,[9]Staff!B$7:H$245,7,0) -> 25305 | H69: =VLOOKUP(B69,[9]Staff!B$7:P$245,15,0) -> 25305 | I69: =VLOOKUP(B69,[2]sales!$B$2:$G$183,6,0) -> Bakery South | J69: CPD | K69: YRFM | L69: =IF(H69>23335,0,(H69*90%*4.75%)) -> 0 | M69: =IF(H69*60%*12%>1800,1974,(H69*60%*13.16%)) -> 1974 | N69: =H69+L69+M69 -> 27279
A70: 69 | B70: 3355 | C70: Krishnaprasad V.S. | D70: =VLOOKUP(B70,[2]sales!$B$2:$D$183,3,0) -> Territory Sales Executive | E70: 26.06.2014 | F70: S1 | G70: =VLOOKUP(B70,'[3]april (2)'!B$8:H$132,7,0) -> 14550 | H70: =VLOOKUP(B70,'[3]april (2)'!B$8:N$132,13,0) -> 14550 | I70: =VLOOKUP(B70,[2]sales!$B$2:$G$183,6,0) -> CPD South | J70: CPD | K70: Agro | L70: =IF(H70>23335,0,(H70*90%*4.75%)) -> 622.0125 | M70: =IF(H70*60%*12%>1800,1974,(H70*60%*13.16%)) -> 1148.868 | N70: =H70+L70+M70 -> 16320.88
A71: 70 | B71: 2961 | C71: Ranjith K.S | D71: Merchandiser | E71: 25.10.2012 | F71: S1 | G71: =VLOOKUP(B71,[9]Staff!B$7:H$245,7,0) -> 12710 | H71: =VLOOKUP(B71,[9]Staff!B$7:P$245,15,0) -> 12710 | I71: CPD | J71: CPD | K71: YRFM | L71: =IF(H71>23335,0,(H71*90%*4.75%)) -> 543.3525 | M71: =IF(H71*60%*12%>1800,1974,(H71*60%*13.16%)) -> 1003.5816 | N71: =H71+L71+M71 -> 14256.934
A72: 71 | B72: 3005 | C72: P. Gopi | D72: =VLOOKUP(B72,[2]sales!$B$2:$D$183,3,0) -> Area Sales Manager | E72: 01.12.2012 | F72: M1 | G72: =VLOOKUP(B72,[9]Staff!B$7:H$245,7,0) -> 48340 | H72: =VLOOKUP(B72,[9]Staff!B$7:P$245,15,0) -> 48340 | I72: =VLOOKUP(B72,[2]sales!$B$2:$G$183,6,0) -> Tamilnadu | J72: Tamil Nadu | K72: YRFM | L72: =IF(H72>23335,0,(H72*90%*4.75%)) -> 0 | M72: =IF(H72*60%*12%>1800,1974,(H72*60%*13.16%)) -> 1974 | N72: =H72+L72+M72 -> 50314
A73: 72 | B73: 5009 | C73: Balu.G | D73: Territory Sales Executive | E73: 24.04.2018 | F73: S1 | G73: =VLOOKUP(B73,'[5]Hosur-Apr''18'!B$5:H$127,7,0) -> 19000 | H73: =VLOOKUP(B73,'[5]Hosur-Apr''18'!B$5:M$127,12,0) -> 4446 | I73: Tamilnadu | K73: Hosur | L73: =IF(H73>21000,0,(H73*4.75%)) -> 211.185 | M73: =IF(H73*70%*12%>1800,1974,(H73*70%*12%)) -> 373.464 | N73: =H73+L73+M73 -> 5030.649
A74: 73 | B74: 3006 | C74: P. Senthilkumar | D74: =VLOOKUP(B74,[2]sales!$B$2:$D$183,3,0) -> Area Sales Manager | E74: 04.10.2010 | F74: M1 | G74: =VLOOKUP(B74,[9]Staff!B$7:H$245,7,0) -> 48740 | H74: =VLOOKUP(B74,[9]Staff!B$7:P$245,15,0) -> 48740 | I74: =VLOOKUP(B74,[2]sales!$B$2:$G$183,6,0) -> Tamilnadu | J74: Tamil Nadu | K74: YRFM | L74: =IF(H74>23335,0,(H74*90%*4.75%)) -> 0 | M74: =IF(H74*60%*12%>1800,1974,(H74*60%*13.16%)) -> 1974 | N74: =H74+L74+M74 -> 50714
A75: 74 | B75: 3009 | C75: Arulmozhi S | D75: =VLOOKUP(B75,[2]sales!$B$2:$D$183,3,0) -> Territory Sales Executive | E75: 14.06.2011 | F75: S1 | G75: =VLOOKUP(B75,[9]Staff!B$7:H$245,7,0) -> 21990 | H75: =VLOOKUP(B75,[9]Staff!B$7:P$245,15,0) -> 21990 | I75: =VLOOKUP(B75,[2]sales!$B$2:$G$183,6,0) -> Tamilnadu | J75: Tamil Nadu | K75: YRFM | L75: =IF(H75>23335,0,(H75*90%*4.75%)) -> 940.0725 | M75: =IF(H75*60%*12%>1800,1974,(H75*60%*13.16%)) -> 1736.3304 | N75: =H75+L75+M75 -> 24666.403
A76: 75 | B76: 3024 | C76: Shibu Samuel | D76: =VLOOKUP(B76,[2]sales!$B$2:$D$183,3,0) -> Territory Sales Executive | E76: 10.12.2012 | F76: S1 | G76: =VLOOKUP(B76,'[3]april (2)'!B$8:H$132,7,0) -> 17860 | H76: =VLOOKUP(B76,'[3]april (2)'!B$8:N$132,13,0) -> 17860 | I76: =VLOOKUP(B76,[2]sales!$B$2:$G$183,6,0) -> Institution Sales | J76: Agro Sales | K76: Agro | L76: =IF(H76>23335,0,(H76*90%*4.75%)) -> 763.515 | M76: =IF(H76*60%*12%>1800,1974,(H76*60%*13.16%)) -> 1410.2256 | N76: =H76+L76+M76 -> 20033.741
A77: 76 | B77: 3053 | C77: Sujith O.S | D77: =VLOOKUP(B77,[2]sales!$B$2:$D$183,3,0) -> Territory Sales Executive | E77: 24.12.2012 | F77: S1 | G77: =VLOOKUP(B77,'[3]april (2)'!B$8:H$132,7,0) -> 17230 | H77: =VLOOKUP(B77,'[3]april (2)'!B$8:N$132,13,0) -> 17230 | I77: =VLOOKUP(B77,[2]sales!$B$2:$G$183,6,0) -> Institution Sales | J77: Agro Sales | K77: Agro | L77: =IF(H77>23335,0,(H77*90%*4.75%)) -> 736.5825 | M77: =IF(H77*60%*12%>1800,1974,(H77*60%*13.16%)) -> 1360.4808 | N77: =H77+L77+M77 -> 19327.063
A78: 77 | B78: 3059 | C78: Ramesh.S | D78: =VLOOKUP(B78,[2]sales!$B$2:$D$183,3,0) -> Territory Sales Executive | E78: 04.02.2013 | F78: S1 | G78: =VLOOKUP(B78,[9]Staff!B$7:H$245,7,0) -> 18690 | H78: =VLOOKUP(B78,[9]Staff!B$7:P$245,15,0) -> 18690 | I78: =VLOOKUP(B78,[2]sales!$B$2:$G$183,6,0) -> Tamilnadu | J78: Tamil Nadu | K78: YRFM | L78: =IF(H78>23335,0,(H78*90%*4.75%)) -> 798.9975 | M78: =IF(H78*60%*12%>1800,1974,(H78*60%*13.16%)) -> 1475.7624 | N78: =H78+L78+M78 -> 20964.76
A79: 78 | B79: 3092 | C79: Dinesh Kumar C | D79: =VLOOKUP(B79,[2]sales!$B$2:$D$183,3,0) -> Sr. Territory Sales Executive | E79: 01.03.2013 | F79: S2 | G79: =VLOOKUP(B79,[9]Staff!B$7:H$245,7,0) -> 25580 | H79: =VLOOKUP(B79,[9]Staff!B$7:P$245,15,0) -> 25580 | I79: =VLOOKUP(B79,[2]sales!$B$2:$G$183,6,0) -> Tamilnadu | J79: Tamil Nadu | K79: YRFM | L79: =IF(H79>23335,0,(H79*90%*4.75%)) -> 0 | M79: =IF(H79*60%*12%>1800,1974,(H79*60%*13.16%)) -> 1974 | N79: =H79+L79+M79 -> 27554
A80: 79 | B80: 3114 | C80: Sreekanth M.S | D80: =VLOOKUP(B80,[2]sales!$B$2:$D$183,3,0) -> Territory Sales Executive | E80: 22.04.2013 | F80: S1 | G80: =VLOOKUP(B80,[9]Staff!B$7:H$245,7,0) -> 14000 | H80: =VLOOKUP(B80,[9]Staff!B$7:P$245,15,0) -> 14000 | I80: =VLOOKUP(B80,[2]sales!$B$2:$G$183,6,0) -> Bakery South | J80: Bread & Cakes | K80: YRFM | L80: =IF(H80>23335,0,(H80*90%*4.75%)) -> 598.5 | M80: =IF(H80*60%*12%>1800,1974,(H80*60%*13.16%)) -> 1105.44 | N80: =H80+L80+M80 -> 15703.94
A81: 80 | B81: 3189 | C81: Sudheer K.V | D81: Merchandiser | E81: 10.02.1991 | F81: F2 | G81: =VLOOKUP(B81,'[6]staff klmsy (2)'!$B$7:I$84,8,0) -> 21870 | H81: =VLOOKUP(B81,'[6]staff klmsy (2)'!B$7:R$84,17,0) -> 21870 | I81: South Kerala Bakery | J81: Bread & Cakes | K81: Kalamassery | L81: =IF(H81>23335,0,(H81*90%*4.75%)) -> 934.9425 | M81: =IF(H81*60%*12%>1800,1974,(H81*60%*13.16%)) -> 1726.8552 | N81: =H81+L81+M81 -> 24531.798
A82: 81 | B82: 3190 | C82: Santhosh Kumar .K | D82: Merchandiser | E82: 10.03.1990 | F82: F2 | G82: =VLOOKUP(B82,'[6]staff klmsy (2)'!$B$7:I$84,8,0) -> 21150 | H82: =VLOOKUP(B82,'[6]staff klmsy (2)'!B$7:R$84,17,0) -> 21150 | I82: South Kerala Bakery | J82: Cake Plus | K82: Kalamassery | L82: =IF(H82>23335,0,(H82*90%*4.75%)) -> 904.1625 | M82: =IF(H82*60%*12%>1800,1974,(H82*60%*13.16%)) -> 1670.004 | N82: =H82+L82+M82 -> 23724.166
A83: 82 | B83: 3191 | C83: Harshakumar | D83: =VLOOKUP(B83,[2]sales!$B$2:$D$183,3,0) -> Territory Sales Executive | E83: 04.04.1995 | F83: S2 | G83: =VLOOKUP(B83,'[6]staff klmsy (2)'!$B$7:I$84,8,0) -> 22430 | H83: =VLOOKUP(B83,'[6]staff klmsy (2)'!B$7:R$84,17,0) -> 22430 | I83: =VLOOKUP(B83,[2]sales!$B$2:$G$183,6,0) -> Bakery South | J83: Bread & Cakes | K83: Kalamassery | L83: =IF(H83>23335,0,(H83*90%*4.75%)) -> 958.8825 | M83: =IF(H83*60%*12%>1800,1974,(H83*60%*13.16%)) -> 1771.0728 | N83: =H83+L83+M83 -> 25159.955
A84: 83 | B84: 3205 | C84: Binoy Joseph | D84: =VLOOKUP(B84,[2]sales!$B$2:$D$183,3,0) -> Territory Sales Executive | E84: 01.01.2014 | F84: S1 | G84: =VLOOKUP(B84,[9]Staff!B$7:H$245,7,0) -> 14890 | H84: =VLOOKUP(B84,[9]Staff!B$7:P$245,15,0) -> 14890 | I84: =VLOOKUP(B84,[2]sales!$B$2:$G$183,6,0) -> Bulk | J84: Bulk | K84: YRFM | L84: =IF(H84>23335,0,(H84*90%*4.75%)) -> 636.5475 | M84: =IF(H84*60%*12%>1800,1974,(H84*60%*13.16%)) -> 1175.7144 | N84: =H84+L84+M84 -> 16702.262
A85: 84 | B85: 3221 | C85: Thirumalai Kumaran.V | D85: =VLOOKUP(B85,[2]sales!$B$2:$D$183,3,0) -> Sr. Territory Sales Executive | E85: 11.02.2014 | F85: S2 | G85: =VLOOKUP(B85,[9]Staff!B$7:H$245,7,0) -> 18060 | H85: =VLOOKUP(B85,[9]Staff!B$7:P$245,15,0) -> 18060 | I85: =VLOOKUP(B85,[2]sales!$B$2:$G$183,6,0) -> Tamilnadu | J85: Tamil Nadu | K85: YRFM | L85: =IF(H85>23335,0,(H85*90%*4.75%)) -> 772.065 | M85: =IF(H85*60%*12%>1800,1974,(H85*60%*13.16%)) -> 1426.0176 | N85: =H85+L85+M85 -> 20258.083
A86: 85 | B86: 3239 | C86: Prabhakaran K V | D86: =VLOOKUP(B86,[2]sales!$B$2:$D$183,3,0) -> Sr. Territory Sales Executive | E86: 20.02.2010 | F86: S2 | G86: =VLOOKUP(B86,'[3]april (2)'!B$8:H$132,7,0) -> 21390 | H86: =VLOOKUP(B86,'[3]april (2)'!B$8:N$132,13,0) -> 17825 | I86: =VLOOKUP(B86,[2]sales!$B$2:$G$183,6,0) -> CPD South | J86: CPD | K86: Agro | L86: =IF(H86>23335,0,(H86*90%*4.75%)) -> 762.01875 | M86: =IF(H86*60%*12%>1800,1974,(H86*60%*13.16%)) -> 1407.462 | N86: =H86+L86+M86 -> 19994.481
A87: 86 | B87: 3244 | C87: Girish P V | D87: Vansale Representative | E87: 26.07.2010 | F87: S1 | G87: =VLOOKUP(B87,'[3]april (2)'!B$8:H$132,7,0) -> 20930 | H87: =VLOOKUP(B87,'[3]april (2)'!B$8:N$132,13,0) -> 20930 | I87: CPD | J87: CPD | K87: Agro | L87: =IF(H87>23335,0,(H87*90%*4.75%)) -> 894.7575 | M87: =IF(H87*60%*12%>1800,1974,(H87*60%*13.16%)) -> 1652.6328 | N87: =H87+L87+M87 -> 23477.39
A88: 87 | B88: 3245 | C88: Shakeer A | D88: Merchandiser | E88: 27.09.2010 | F88: S1 | G88: =VLOOKUP(B88,'[3]april (2)'!B$8:H$132,7,0) -> 18510 | H88: =VLOOKUP(B88,'[3]april (2)'!B$8:N$132,13,0) -> 18510 | I88: CPD | J88: CPD | K88: Agro | L88: =IF(H88>23335,0,(H88*90%*4.75%)) -> 791.3025 | M88: =IF(H88*60%*12%>1800,1974,(H88*60%*13.16%)) -> 1461.5496 | N88: =H88+L88+M88 -> 20762.852
A89: 88 | B89: 3249 | C89: Shaji.Damodaran . | D89: Vansale Representative | E89: 20.12.2010 | F89: S1 | G89: =VLOOKUP(B89,'[3]april (2)'!B$8:H$132,7,0) -> 17540 | H89: =VLOOKUP(B89,'[3]april (2)'!B$8:N$132,13,0) -> 17540 | I89: CPD | J89: CPD | K89: Agro | L89: =IF(H89>23335,0,(H89*90%*4.75%)) -> 749.835 | M89: =IF(H89*60%*12%>1800,1974,(H89*60%*13.16%)) -> 1384.9584 | N89: =H89+L89+M89 -> 19674.793
A90: 89 | B90: 3252 | C90: Dileep Kumar N | D90: Vansale Representative | E90: 03.02.2011 | F90: S1 | G90: =VLOOKUP(B90,'[3]april (2)'!B$8:H$132,7,0) -> 17540 | H90: =VLOOKUP(B90,'[3]april (2)'!B$8:N$132,13,0) -> 17540 | I90: CPD | J90: CPD | K90: Agro | L90: =IF(H90>23335,0,(H90*90%*4.75%)) -> 749.835 | M90: =IF(H90*60%*12%>1800,1974,(H90*60%*13.16%)) -> 1384.9584 | N90: =H90+L90+M90 -> 19674.793
A91: 90 | B91: 3259 | C91: Jithesh.R | D91: Vansale Representative | E91: 20.02.2012 | F91: S1 | G91: =VLOOKUP(B91,'[3]april (2)'!B$8:H$132,7,0) -> 14820 | H91: =VLOOKUP(B91,'[3]april (2)'!B$8:N$132,13,0) -> 14820 | I91: CPD | J91: CPD | K91: Agro | L91: =IF(H91>23335,0,(H91*90%*4.75%)) -> 633.555 | M91: =IF(H91*60%*12%>1800,1974,(H91*60%*13.16%)) -> 1170.1872 | N91: =H91+L91+M91 -> 16623.742
A92: 91 | B92: 3265 | C92: Sumesh E.G | D92: =VLOOKUP(B92,[2]sales!$B$2:$D$183,3,0) -> Territory Sales Executive | E92: 03.09.2012 | F92: S1 | G92: =VLOOKUP(B92,'[3]april (2)'!B$8:H$132,7,0) -> 16760 | H92: =VLOOKUP(B92,'[3]april (2)'!B$8:N$132,13,0) -> 16760 | I92: =VLOOKUP(B92,[2]sales!$B$2:$G$183,6,0) -> Bulk | J92: CPD | K92: Agro | L92: =IF(H92>23335,0,(H92*90%*4.75%)) -> 716.49 | M92: =IF(H92*60%*12%>1800,1974,(H92*60%*13.16%)) -> 1323.3696 | N92: =H92+L92+M92 -> 18799.86
A93: 92 | B93: 3269 | C93: Dileep K | D93: =VLOOKUP(B93,[2]sales!$B$2:$D$183,3,0) -> Territory Sales Manager | E93: 19.10.2012 | F93: P3 | G93: =VLOOKUP(B93,'[3]april (2)'!B$8:H$132,7,0) -> 20000 | H93: =VLOOKUP(B93,'[3]april (2)'!B$8:N$132,13,0) -> 20000 | I93: =VLOOKUP(B93,[2]sales!$B$2:$G$183,6,0) -> Modern Trade | J93: Modern Trade | K93: Agro | L93: =IF(H93>23335,0,(H93*90%*4.75%)) -> 855 | M93: =IF(H93*60%*12%>1800,1974,(H93*60%*13.16%)) -> 1579.2 | N93: =H93+L93+M93 -> 22434.2
A94: 93 | B94: 3287 | C94: Shihab.Y | D94: =VLOOKUP(B94,[2]sales!$B$2:$D$183,3,0) -> Territory Sales Executive | E94: 26.08.2013 | F94: S1 | G94: =VLOOKUP(B94,'[3]april (2)'!B$8:H$132,7,0) -> 16590 | H94: =VLOOKUP(B94,'[3]april (2)'!B$8:N$132,13,0) -> 16590 | I94: =VLOOKUP(B94,[2]sales!$B$2:$G$183,6,0) -> institution Sales | J94: Institutional Sales | K94: Agro | L94: =IF(H94>23335,0,(H94*90%*4.75%)) -> 709.2225 | M94: =IF(H94*60%*12%>1800,1974,(H94*60%*13.16%)) -> 1309.9464 | N94: =H94+L94+M94 -> 18609.169
A95: 94 | B95: 3299 | C95: Rakesh P.R. | D95: Merchandiser | E95: 07.04.2014 | F95: S1 | G95: =VLOOKUP(B95,[9]Staff!B$7:H$245,7,0) -> 13920 | H95: =VLOOKUP(B95,[9]Staff!B$7:P$245,15,0) -> 13920 | I95: CPD | J95: CPD | K95: YRFM | L95: =IF(H95>23335,0,(H95*90%*4.75%)) -> 595.08 | M95: =IF(H95*60%*12%>1800,1974,(H95*60%*13.16%)) -> 1099.1232 | N95: =H95+L95+M95 -> 15614.203
A96: 95 | B96: 3321 | C96: Manoj .K | D96: =VLOOKUP(B96,[2]sales!$B$2:$D$183,3,0) -> Territory Sales Manager | E96: 28.04.2014 | F96: P3 | G96: =VLOOKUP(B96,'[3]april (2)'!B$8:H$132,7,0) -> 40880 | H96: =VLOOKUP(B96,'[3]april (2)'!B$8:N$132,13,0) -> 40880 | I96: =VLOOKUP(B96,[2]sales!$B$2:$G$183,6,0) -> CPD North | J96: CPD | K96: Agro | L96: =IF(H96>23335,0,(H96*90%*4.75%)) -> 0 | M96: =IF(H96*60%*12%>1800,1974,(H96*60%*13.16%)) -> 1974 | N96: =H96+L96+M96 -> 42854
A97: 96 | B97: 3329 | C97: K.Balaji. | D97: =VLOOKUP(B97,[2]sales!$B$2:$D$183,3,0) -> Territory Sales Executive | E97: 30.05.2014 | F97: S1 | G97: =VLOOKUP(B97,[9]Staff!B$7:H$245,7,0) -> 18830 | H97: =VLOOKUP(B97,[9]Staff!B$7:P$245,15,0) -> 18830 | I97: =VLOOKUP(B97,[2]sales!$B$2:$G$183,6,0) -> Tamilnadu | J97: Tamil Nadu | K97: YRFM | L97: =IF(H97>23335,0,(H97*90%*4.75%)) -> 804.9825 | M97: =IF(H97*60%*12%>1800,1974,(H97*60%*13.16%)) -> 1486.8168 | N97: =H97+L97+M97 -> 21121.799
A98: 97 | B98: 3330 | C98: Sreejith.S.Nair . | D98: =VLOOKUP(B98,[2]sales!$B$2:$D$183,3,0) -> Territory Sales Manager | E98: 02.06.2014 | F98: P3 | G98: =VLOOKUP(B98,[9]Staff!B$7:H$245,7,0) -> 25750 | H98: =VLOOKUP(B98,[9]Staff!B$7:P$245,15,0) -> 25750 | I98: =VLOOKUP(B98,[2]sales!$B$2:$G$183,6,0) -> CPD South | J98: CPD | K98: YRFM | L98: =IF(H98>23335,0,(H98*90%*4.75%)) -> 0 | M98: =IF(H98*60%*12%>1800,1974,(H98*60%*13.16%)) -> 1974 | N98: =H98+L98+M98 -> 27724
A99: 98 | B99: 3335 | C99: P.K.Selvakumar | D99: =VLOOKUP(B99,[2]sales!$B$2:$D$183,3,0) -> Territory Sales Executive | E99: 02.06.2014 | F99: S1 | G99: =VLOOKUP(B99,[9]Staff!B$7:H$245,7,0) -> 16980 | H99: =VLOOKUP(B99,[9]Staff!B$7:P$245,15,0) -> 16980 | I99: =VLOOKUP(B99,[2]sales!$B$2:$G$183,6,0) -> Tamilnadu | J99: Tamil Nadu | K99: YRFM | L99: =IF(H99>23335,0,(H99*90%*4.75%)) -> 725.895 | M99: =IF(H99*60%*12%>1800,1974,(H99*60%*13.16%)) -> 1340.7408 | N99: =H99+L99+M99 -> 19046.636
A100: 99 | B100: 3347 | C100: G.Sampath | D100: =VLOOKUP(B100,[2]sales!$B$2:$D$183,3,0) -> Territory Sales Executive | E100: 02.06.2014 | F100: S1 | G100: =VLOOKUP(B100,[9]Staff!B$7:H$245,7,0) -> 19280 | H100: =VLOOKUP(B100,[9]Staff!B$7:P$245,15,0) -> 19280 | I100: =VLOOKUP(B100,[2]sales!$B$2:$G$183,6,0) -> Tamilnadu | J100: Tamil Nadu | K100: YRFM | L100: =IF(H100>23335,0,(H100*90%*4.75%)) -> 824.22 | M100: =IF(H100*60%*12%>1800,1974,(H100*60%*13.16%)) -> 1522.3488 | N100: =H100+L100+M100 -> 21626.569
...

Sheet Quota
A1: Emp.No | B1: Quota
A2: 6 | B2: 12
A3: 10 | B3: 12
A4: 11 | B4: 12
A5: 16 | B5: 12
A6: 17 | B6: 12
A7: 18 | B7: 12
A8: 19 | B8: 12
A9: 20 | B9: 12
A10: 5264 | B10: 12
A11: 55 | B11: 12
A12: 57 | B12: 12
A13: 61 | B13: 12
... A310: 6492 | B310: 12
A311: 2721 | B311: 12
A312: 3613 | B312: 12
A313: 3615 | B313: 12
A314: 5458 | B314: 12
A315: 5906 | B315: 12
A316: 5914 | B316: 12
A317: 5922 | B317: 12
A318: 5942 | B318: 12
A319: 5977 | B319: 12
A320: 6039 | B320: 12
A321: 6146 | B321: 12
A322: 6197 | B322: 12
A323: 6205 | B323: 12
A324: 6264 | B324: 12
A325: 6350 | B325: 12
... A522: 5489 | B522: 12
A523: 1335 | B523: 12
A524: 4552 | B524: 12
A525: 4949 | B525: 12
A526: 5211 | B526: 12
A527: 5400 | B527: 12
A528: 5598 | B528: 12
A529: 5698 | B529: 12
A530: 5784 | B530: 12
A531: 5785 | B531: 12
A532: 5801 | B532: 12
A533: 5827 | B533: 12
A534: 5845 | B534: 12
A535: 5908 | B535: 12
... A718: 5961 | B718: 12
